task_manager_sdk/__init__.py
task_manager_sdk/client.py
task_manager_sdk/tasks.py
tests/__init__.py
tests/test_client.py
tests/test_tasks.py
task_manager_sdk-0.2.2.dist-info/METADATA
task_manager_sdk-0.2.2.dist-info/WHEEL
task_manager_sdk-0.2.2.dist-info/top_level.txt
task_manager_sdk-0.2.2.dist-info/RECORD
