Metadata-Version: 2.1
Name: task_manager_sdk
Version: 0.2.2
Summary: Un SDK para interactuar con la API TaskManager
Home-page: https://github.com/tuusuario/task_manager_sdk
Author: Tu Nombre
Author-email: tuemail@example.com
Requires-Dist: requests >=2.25.1
